{
  "classNumber": "01",
  "chapterName": "LCM & HCF",
  "sections": [
    {
      "type": "title",
      "content": "মৌলিক ধারণা (Basic Concepts)"
    },
    {
      "type": "math",
      "content": "LCM × HCF = Product of Two Numbers"
    },
    {
      "type": "box",
      "title": "মনে রাখবে",
      "content": "গসাগু সর্বদা লসাগু এর একটি উৎপাদক হয়।"
    },
    {
      "type": "list",
      "items": [
        "দুটি মৌলিক সংখ্যার গসাগু সর্বদা ১ হয়।",
        "ভগ্নাংশের লসাগু = (লবগুলির লসাগু) / (হরগুলির গসাগু)"
      ]
    }
  ]
}